LICENSE
MANIFEST.in
README.rst
setup.py
keras_mixed_sequence/__init__.py
keras_mixed_sequence/__version__.py
keras_mixed_sequence/keras_mixed_sequence.py
keras_mixed_sequence.egg-info/PKG-INFO
keras_mixed_sequence.egg-info/SOURCES.txt
keras_mixed_sequence.egg-info/dependency_links.txt
keras_mixed_sequence.egg-info/requires.txt
keras_mixed_sequence.egg-info/top_level.txt
keras_mixed_sequence/utils/__init__.py
keras_mixed_sequence/utils/sequence.py
keras_mixed_sequence/utils/vector_sequence.py