Metadata-Version: 2.1
Name: keras-mixed-sequence
Version: 1.0.29
Summary: Lazily loading mixed sequences using Keras Sequence, focused on multi-task models.
Home-page: https://github.com/LucaCappelletti94/keras_mixed_sequence
Author: Luca Cappelletti
Author-email: cappelletti.luca94@gmail.com
License: MIT
Platform: UNKNOWN
Classifier: Development Status :: 3 - Alpha
Classifier: License :: OSI Approved :: MIT License
Classifier: Programming Language :: Python :: 3
Requires-Python: >3.5.2
Provides-Extra: test
License-File: LICENSE
